yta_main/__init__.py
yta_main/project.json
yta_main-0.0.2.dist-info/LICENSE
yta_main-0.0.2.dist-info/METADATA
yta_main-0.0.2.dist-info/WHEEL
yta_main-0.0.2.dist-info/RECORD
